TensorflowZhongwenWendang18Juejin2018519/README.md
TensorflowZhongwenWendang18Juejin2018519/__init__.py
TensorflowZhongwenWendang18Juejin2018519/__main__.py
TensorflowZhongwenWendang18Juejin2018519/file.epub
TensorflowZhongwenWendang18Juejin2018519/index.html
TensorflowZhongwenWendang18Juejin2018519/css/__init__.py
TensorflowZhongwenWendang18Juejin2018519/css/annotations.css
TensorflowZhongwenWendang18Juejin2018519/css/main.css
TensorflowZhongwenWendang18Juejin2018519/css/normalize.css
TensorflowZhongwenWendang18Juejin2018519/css/popup.css
TensorflowZhongwenWendang18Juejin2018519/font/__init__.py
TensorflowZhongwenWendang18Juejin2018519/font/fontello.eot
TensorflowZhongwenWendang18Juejin2018519/font/fontello.svg
TensorflowZhongwenWendang18Juejin2018519/font/fontello.ttf
TensorflowZhongwenWendang18Juejin2018519/font/fontello.woff
TensorflowZhongwenWendang18Juejin2018519/img/__init__.py
TensorflowZhongwenWendang18Juejin2018519/img/annotator-glyph-sprite.png
TensorflowZhongwenWendang18Juejin2018519/img/annotator-icon-sprite.png
TensorflowZhongwenWendang18Juejin2018519/img/apple-touch-icon.png
TensorflowZhongwenWendang18Juejin2018519/img/cancelfullscreen.png
TensorflowZhongwenWendang18Juejin2018519/img/close.png
TensorflowZhongwenWendang18Juejin2018519/img/fullscreen.png
TensorflowZhongwenWendang18Juejin2018519/img/loader.gif
TensorflowZhongwenWendang18Juejin2018519/img/menu-icon.png
TensorflowZhongwenWendang18Juejin2018519/img/save.png
TensorflowZhongwenWendang18Juejin2018519/img/saved.png
TensorflowZhongwenWendang18Juejin2018519/img/settings-s.png
TensorflowZhongwenWendang18Juejin2018519/img/settings.png
TensorflowZhongwenWendang18Juejin2018519/img/star.png
TensorflowZhongwenWendang18Juejin2018519/js/__init__.py
TensorflowZhongwenWendang18Juejin2018519/js/epub.js
TensorflowZhongwenWendang18Juejin2018519/js/epub.min.js
TensorflowZhongwenWendang18Juejin2018519/js/epub.min.map
TensorflowZhongwenWendang18Juejin2018519/js/hooks.min.js
tensorflow_zhongwen_wendang_1_8_juejin_2018_5_19-2024.3.3.0.dist-info/METADATA
tensorflow_zhongwen_wendang_1_8_juejin_2018_5_19-2024.3.3.0.dist-info/WHEEL
tensorflow_zhongwen_wendang_1_8_juejin_2018_5_19-2024.3.3.0.dist-info/entry_points.txt
tensorflow_zhongwen_wendang_1_8_juejin_2018_5_19-2024.3.3.0.dist-info/top_level.txt
tensorflow_zhongwen_wendang_1_8_juejin_2018_5_19-2024.3.3.0.dist-info/RECORD
